Workbook

Sheet Que of the assignment
B3: Assignment Question: Merger Model for LinkedIn and Microsoft Deal
B5: Objective:
B6: Candidates are required to prepare a detailed merger model for the acquisition of LinkedIn by Microsoft, which was announced on June 13, 2016. The model should incorporate both qualitative and quantitative analysis to provide a comprehensive overview of the deal.
B8: Instructions:
B10: 1. Introduction:
B11: Provide a brief introduction to LinkedIn and Microsoft.
B12: Outline the strategic rationale behind the merger.
B13: Mention the key terms of the deal, including the acquisition price and method of payment.
B15: 2. Historical Financial Analysis:
B16: Analyze the historical financial statements of both companies for the past three years.
B17: Include income statements, balance sheets, and cash flow statements.
B18: Calculate key financial ratios and metrics to understand the financial health and performance pre-merger.
... B33: An Excel model with all calculations and financial statements.

Sheet Introduction
B2: Merger model of Microsoft & Linked In
B3: Acquirer Company : Microsoft (MSFT)
B4: Tartget Company : LinkedIn (LNKD)
B6: Microsoft Corporation | D6: LinkedIn Corporation
B7: Founded: 1975 | D7: Founded: 2002
B8: Headquarters: Redmond, Washington | D8: Headquarters: Sunnyvale, California
B9: Key Products: Windows OS, Microsoft Office, Azure Cloud, Dynamics CRM | D9: Users (2016): Over 433 million members
B10: Business model | D10: Business Model:
B11: Software and cloud services | D11: Professional networking
B12: Enterprise solutions | D12: Job listings
B13: Hardware and devices | D13: Premium subscriptions
B14: Strategic Focus (2016): Cloud computing, AI, productivity tools, and enterprise | D14: Talent and marketing solutions
B15: integration | D15: Core Strength: Largest global platform for professionals to connect, learn, and find opportunities
B18: Key Details of the Acquisition:
B19: Transaction Value: $26.2 billion, including LinkedIn's net cash.
B20: Price per Share: $196.
B21: Leadership: Jeff Weiner to remain LinkedIn CEO, reporting to Satya Nadella.
B22: Brand and Independence: LinkedIn to retain its distinct brand, culture, and independence.
B23: Strategic Fit: Microsoft aimed to integrate LinkedIn with its enterprise software, like Office 365, and leverage its large user base.
B25: Analyst Commentary:
B26: Analysts noted that Microsoft could build LinkedIn into a major customer relationship management (CRM) platform, competing with Salesforce.
B27: Some analysts also pointed out that the deal gave Microsoft access to the world's largest professional social network .
B29: Impact on Microsoft and LinkedIn:
B30: Microsoft: Gained access to LinkedIn's massive user base and a prominent professional networking platform, strengthening its enterprise offerings.
B31: LinkedIn: Benefited from Microsoft's resources and support, accelerating its growth and expanding its global reach.

Sheet Synergies
B4: On Monday, June 13, 2016, Microsoft (MSFT) announced the acquisition of LinkedIn for $26.2 billion in an all-cash transaction, valuing each share at $196. The deal was fully supported by LinkedIn's chairman and co-founder, Reid Hoffman, and CEO, Jeff Weiner, who would remain in his role and report to Microsoft CEO Satya Nadella. LinkedIn would retain its distinct brand, culture, and independence.
B7: Strategic Rationale Behind the Merger
B8: The acquisition of LinkedIn by Microsoft in June 2016 for $26.2 billion was driven by a shared vision: to connect the world's leading professional cloud with the world's leading professional network. The strategic rationale includes the following key points:
B10: 🔗 1. Synergy Between Products and Platforms
B11: Microsoft aimed to integrate LinkedIn’s professional graph with its productivity suite (Office 365, Outlook, Dynamics CRM).
B12: This would help users enhance their work through intelligent insights, networking, and collaboration.
B13: 📈 2. Accelerated Engagement and Growth
B14: LinkedIn had shown strong user growth and engagement:
B15: 19% growth in total membership
B16: 49% growth in mobile usage
B17: 101% increase in job listings
B18: Microsoft could leverage this momentum to boost both companies’ reach and user base.
... B48: Facilitating communication with regulators and shareholders

Sheet Microsoft  acquirer
A2: Merger model of Microsoft & Linked In
A3: Acquirer Company : Microsoft (MSFT)
A4: Tartget Company : LinkedIn (LNKD)
A5: Date of Acquisition : 13/06/2016
A6: Price of acquisition : $26.2 Billion
A7: ($ in million except per share data)
A9: Acquirer details
B11: Latest Financials available | D11: 42551 | G11: Capitalisation of Lease
B12: Unaffected share price | D12: 48.03 | G12: Year | H12: Amount | I12: lease committed
B13: Transaction date share price | D13: 50.14 | G13: 2016 | H13: 863
B14: Tax rate | D14: 0.34 | G14: =G13+1 -> 2017 | H14: 803
G15: =G14+1 -> 2018 | H15: 735
B16: Basic shares outstaning | D16: 8177 | G16: =G15+1 -> 2019 | H16: 611
B17: Dilutive shares outstanding | D17: 8254 | G17: =G16+1 -> 2020 | H17: 524 | I17: 1617
G18: =G17+1 -> 2021 | H18: 524 | I18: =I17-H18 -> 1093
B19: Equity value on date on transaction | D19: =D17*D13 -> 413855.56 | G19: =G18+1 -> 2022 | H19: 524 | I19: =I18-H19 -> 569
B20: Less: Cash | D20: -5595 | G20: =G19+1 -> 2023 | H20: 524 | I20: =I19-H20 -> 45
B21: Less: Investments | D21: -90931 | G21: =G20+1 -> 2024 | H21: 45 | I21: =I20-H21 -> 0
B22: Add: Debt | D22: =4985+2499+27808 -> 35292
B23: Add: Capitalisation of lease | D23: =H24 -> 4716.5213 | G23: cost of debt | H23: =I27/I26 -> 0.022129661
B24: Add: Preference shares | D24: 0 | G24: PV of lease obligation | H24: =NPV(H23,H13:H21) -> 4716.5213
B25: Add: NCI | D25: 0
B26: Add: Unfunded pension obligation | D26: 0 | G26: total debt | I26: =D22 -> 35292
B27: Enterprise value | D27: =SUM(D19:D26) -> 357338.08 | G27: Interest expense | I27: 781
G28: cost of debt | I28: =I27/I26 -> 0.022129661
A30: Acquirers Income Statement | F30: Historical | J30: Projection
A31: (In millions) | E31: 2013 | F31: =E31+1 -> 2014 | G31: =F31+1 -> 2015 | H31: =G31+1 -> 2016 | I31: =H31+1 -> 2017 | J31: =I31+1 -> 2018 | K31: =J31+1 -> 2019 | L31: =K31+1 -> 2020
B33: Revenue | D33: 73723 | E33: 77849 | F33: 86833 | G33: 93580 | H33: =G33*(1+H61) -> 100851.25 | I33: =H33*(1+I61) -> 108687.48 | J33: =I33*(1+J61) -> 117132.59 | K33: =J33*(1+K61) -> 126233.89 | L33: =K33*(1+L61) -> 136042.38
B34: Cost of revenue | D34: 17530 | E34: 20385 | F34: 27078 | G34: 33038 | H34: =H33*H62 -> 31154.247 | I34: =I33*I62 -> 35279.895 | J34: =J33*J62 -> 38519.358 | K34: =K33*K62 -> 40494.357 | L34: =L33*L62 -> 44179.325
B35: Gross margin | D35: =D33-D34 -> 56193 | E35: =E33-E34 -> 57464 | F35: =F33-F34 -> 59755 | G35: =G33-G34 -> 60542 | H35: =H33-H34 -> 69697.001 | I35: =I33-I34 -> 73407.582 | J35: =J33-J34 -> 78613.232 | K35: =K33-K34 -> 85739.538 | L35: =L33-L34 -> 91863.053
B37: Research and development | E37: 10411 | F37: 11381 | G37: 12046 | H37: =H33*H63 -> 13229.163 | I37: =I33*I63 -> 14257.081 | J37: =J33*J63 -> 15364.868 | K37: =K33*K63 -> 16558.732 | L37: =L33*L63 -> 17845.36
B38: Sales and marketing | E38: 15276 | F38: 15811 | G38: 15713 | H38: =H33*H64 -> 18362.356 | I38: =I33*I64 -> 19276.399 | J38: =J33*J64 -> 20589.554 | K38: =K33*K64 -> 22520.538 | L38: =L33*L64 -> 24103.959
B39: General and administrative | E39: 5013 | F39: 4677 | G39: 4611 | H39: =H33*H65 -> 5631.8447 | I39: =I33*I65 -> 5759.6554 | J39: =J33*J65 -> 6173.2485 | K39: =K33*K65 -> 6797.2315 | L39: =L33*L65 -> 7234.8345
B40: Impairment, integration, and restructuring | E40: 0 | F40: 127 | G40: 10011 | H40: 0 | I40: 0 | J40: 0 | K40: 0 | L40: 0
B41: Operating income Ebit | E41: =E35-SUM(E37:E40) -> 26764 | F41: =F35-SUM(F37:F40) -> 27759 | G41: =G35-SUM(G37:G40) -> 18161 | H41: =H35-SUM(H37:H40) -> 32473.637 | I41: =I35-SUM(I37:I40) -> 34114.447 | J41: =J35-SUM(J37:J40) -> 36485.561 | K41: =K35-SUM(K37:K40) -> 39863.036 | L41: =L35-SUM(L37:L40) -> 42678.899
B42: Other income, net | E42: 288 | F42: 61 | G42: 346 | H42: =H41*H67 -> 346.49396 | I42: =I41*I67 -> 362.96985 | J42: =J41*J67 -> 490.87177 | K42: =K41*K67 -> 461.92809 | L42: =L41*L67 -> 507.6159
B44: Income before income taxes | D44: ` | E44: =E41+E42 -> 27052 | F44: =F41+F42 -> 27820 | G44: =G41+G42 -> 18507 | H44: =H41+H42 -> 32820.131 | I44: =I41+I42 -> 34477.417 | J44: =J41+J42 -> 36976.433 | K44: =K41+K42 -> 40324.964 | L44: =L41+L42 -> 43186.515
B45: Provision for income taxes | E45: 5189 | F45: 5746 | G45: 6314 | H45: =H66*H44 -> 8090.447 | I45: =I66*I44 -> 8498.9825 | J45: =J66*J44 -> 9115.0115 | K45: =K66*K44 -> 9940.4536 | L45: =L66*L44 -> 10645.851
B46: Net income | E46: =E44-E45 -> 21863 | F46: =F44-F45 -> 22074 | G46: =G44-G45 -> 12193 | H46: =H44-H45 -> 24729.684 | I46: =I44-I45 -> 25978.435 | J46: =J44-J45 -> 27861.421 | K46: =K44-K45 -> 30384.511 | L46: =L44-L45 -> 32540.664
B48: Earnings per share:
B49: Basic | E49: =E46/E53 -> 2.6105075 | F49: =F46/F53 -> 2.6598385 | G49: =G46/G53 -> 1.4911337 | H49: =H46/H53 -> 3.0242979 | I49: =I46/I53 -> 3.1770129 | J49: =J46/J53 -> 3.4072914 | K49: =K46/K53 -> 3.7158507 | L49: =L46/L53 -> 3.9795358
B50: Diluted | E50: =E46/E54 -> 2.5812279 | F50: =F46/F54 -> 2.62817 | G50: =G46/G54 -> 1.4772232 | H50: =H46/H54 -> 2.9960848 | I50: =I46/I54 -> 3.1473752 | J50: =J46/J54 -> 3.3755054 | K50: =K46/K54 -> 3.6811862 | L50: =L46/L54 -> 3.9424115
B52: Weighted average shares outstanding
B53: Basic | E53: 8375 | F53: 8299 | G53: 8177 | H53: =G53 -> 8177 | I53: =H53 -> 8177 | J53: =I53 -> 8177 | K53: =J53 -> 8177 | L53: =K53 -> 8177
B54: Diluted | E54: 8470 | F54: 8399 | G54: 8254 | H54: =G54 -> 8254 | I54: =H54 -> 8254 | J54: =I54 -> 8254 | K54: =J54 -> 8254 | L54: =K54 -> 8254
B55: Cash dividend declared per common share
F58: Historical | J58: Projection
A59: Income Statement Driver | E59: 2013 | F59: =E59+1 -> 2014 | G59: =F59+1 -> 2015 | H59: =G59+1 -> 2016 | I59: =H59+1 -> 2017 | J59: =I59+1 -> 2018 | K59: =J59+1 -> 2019 | L59: =K59+1 -> 2020
B61: Sales growth rate | E61: =E33/D33-1 -> 0.055966252 | F61: =F33/E33-1 -> 0.1154029 | G61: =G33/F33-1 -> 0.077700874 | H61: 0.077700874 | I61: 0.077700874 | J61: 0.077700874 | K61: 0.077700874 | L61: 0.077700874
B62: Cost of revenue as % of sales | E62: =E34/E33 -> 0.26185307 | F62: =F34/F33 -> 0.31183997 | G62: =G34/G33 -> 0.35304552 | H62: =AVERAGE(E62:G$62) -> 0.30891286 | I62: =AVERAGE(F62:H$62) -> 0.32459945 | J62: =AVERAGE(G62:I$62) -> 0.32885261 | K62: =AVERAGE(H62:J$62) -> 0.3207883 | L62: =AVERAGE(I62:K$62) -> 0.32474679
B63: Research and development as % of sales | E63: =E37/E33 -> 0.13373325 | F63: =F37/F33 -> 0.13106768 | G63: =G37/G33 -> 0.12872409 | H63: =AVERAGE($E$63:$G$63) -> 0.13117501 | I63: =AVERAGE($E$63:$G$63) -> 0.13117501 | J63: =AVERAGE($E$63:$G$63) -> 0.13117501 | K63: =AVERAGE($E$63:$G$63) -> 0.13117501 | L63: =AVERAGE($E$63:$G$63) -> 0.13117501
B64: Sales and marketing as % of sales | E64: =E38/E33 -> 0.19622603 | F64: =F38/F33 -> 0.18208515 | G64: =G38/G33 -> 0.16790981 | H64: =AVERAGE(E$64:G$64) -> 0.18207366 | I64: =AVERAGE(F$64:H$64) -> 0.17735621 | J64: =AVERAGE(G$64:I$64) -> 0.17577989 | K64: =AVERAGE(H$64:J$64) -> 0.17840325 | L64: =AVERAGE(I$64:K$64) -> 0.17717979
B65: General and administrative as % of sales | E65: =E39/E33 -> 0.064393891 | F65: =F39/F33 -> 0.053862011 | G65: =G39/G33 -> 0.049273349 | H65: =AVERAGE(E$65:G$65) -> 0.055843084 | I65: =AVERAGE(F$65:H$65) -> 0.052992815 | J65: =AVERAGE(G$65:I$65) -> 0.052703082 | K65: =AVERAGE(H$65:J$65) -> 0.053846327 | L65: =AVERAGE(I$65:K$65) -> 0.053180741
B66: Provision for income taxes as % of PBT | E66: =E45/E44 -> 0.19181576 | F66: =F45/F44 -> 0.20654206 | G66: =G45/G44 -> 0.34116821 | H66: =AVERAGE($E66:$G$66) -> 0.24650867 | I66: =AVERAGE($E66:$G$66) -> 0.24650867 | J66: =AVERAGE($E66:$G$66) -> 0.24650867 | K66: =AVERAGE($E66:$G$66) -> 0.24650867 | L66: =AVERAGE($E66:$G$66) -> 0.24650867
B67: Other income(expense) as a % of operating income | E67: =E42/E41 -> 0.010760723 | F67: =F42/F41 -> 0.0021974855 | G67: =G42/G41 -> 0.019051814 | H67: =AVERAGE(E$67:G$67) -> 0.010670008 | I67: =AVERAGE(F$67:H$67) -> 0.010639769 | J67: =AVERAGE(G$67:I$67) -> 0.013453864 | K67: =AVERAGE(H$67:J$67) -> 0.01158788 | L67: =AVERAGE(I$67:K$67) -> 0.011893838
B68: Dep and Amortization as %age of sales | E68: =E74/E33 -> 0.048234402 | F68: =F74/F33 -> 0.060023263 | G68: =G74/G33 -> 0.063656764 | H68: =AVERAGE(E68:G68) -> 0.05730481 | I68: =AVERAGE(F68:H68) -> 0.060328279 | J68: =AVERAGE(G68:I68) -> 0.060429951 | K68: =AVERAGE(H68:J68) -> 0.059354347 | L68: =AVERAGE(I68:K68) -> 0.060037526
F70: Historical | J70: Projection
A71: Key metrix | E71: 2013 | F71: =E71+1 -> 2014 | G71: =F71+1 -> 2015 | H71: =G71+1 -> 2016 | I71: =H71+1 -> 2017 | J71: =I71+1 -> 2018 | K71: =J71+1 -> 2019 | L71: =K71+1 -> 2020
B73: EBIT | E73: 26764 | F73: 27759 | G73: 18161 | H73: =H41 -> 32473.637 | I73: =I41 -> 34114.447 | J73: =J41 -> 36485.561 | K73: =K41 -> 39863.036 | L73: =L41 -> 42678.899
B74: Add: Depreciation And Amortization | E74: 3755 | F74: 5212 | G74: 5957 | H74: =H68*H33 -> 5779.2616 | I74: =I68*I33 -> 6556.9285 | J74: =J68*J33 -> 7078.3167 | K74: =K68*K33 -> 7492.5303 | L74: =L68*L33 -> 8167.6478
B75: EBITDA | E75: =E73+E74 -> 30519 | F75: =F73+F74 -> 32971 | G75: =G73+G74 -> 24118 | H75: =H73+H74 -> 38252.899 | I75: =I73+I74 -> 40671.376 | J75: =J73+J74 -> 43563.878 | K75: =K73+K74 -> 47355.567 | L75: =L73+L74 -> 50846.547
B77: Gross Margin | E77: =E35/E33 -> 0.73814693 | F77: =F35/F33 -> 0.68816003 | G77: =G35/G33 -> 0.64695448 | H77: =H35/H33 -> 0.69108714 | I77: =I35/I33 -> 0.67540055 | J77: =J35/J33 -> 0.67114739 | K77: =K35/K33 -> 0.6792117 | L77: =L35/L33 -> 0.67525321
B78: EBITDA Margin | E78: =E75/E33 -> 0.39202816 | F78: =F75/F33 -> 0.37970587 | G78: =G75/G33 -> 0.25772601 | H78: =H75/H33 -> 0.3793002 | I78: =I75/I33 -> 0.3742048 | J78: =J75/J33 -> 0.37191936 | K78: =K75/K33 -> 0.37514145 | L78: =L75/L33 -> 0.3737552
B79: EBIT Margin | E79: =E73/E33 -> 0.34379375 | F79: =F73/F33 -> 0.31968261 | G79: =G73/G33 -> 0.19406925 | H79: =H73/H33 -> 0.32199539 | I79: =I73/I33 -> 0.31387652 | J79: =J73/J33 -> 0.31148941 | K79: =K73/K33 -> 0.31578711 | L79: =L73/L33 -> 0.31371768
B80: Net Margin | E80: =E46/E33 -> 0.28083855 | F80: =F46/F33 -> 0.25421211 | G80: =G46/G33 -> 0.13029493 | H80: =H46/H33 -> 0.2452095 | I80: =I46/I33 -> 0.23901958 | J80: =J46/J33 -> 0.23786225 | K80: =K46/K33 -> 0.2407001 | L80: =L46/L33 -> 0.23919506
A83: Acquirers balance sheet | F83: Historical | J83: Projection
A84: (In millions) | E84: 2013 | F84: =E84+1 -> 2014 | G84: =F84+1 -> 2015 | H84: =G84+1 -> 2016 | I84: =H84+1 -> 2017 | J84: =I84+1 -> 2018 | K84: =J84+1 -> 2019 | L84: =K84+1 -> 2020
B86: Assets
B87: Current assets
B88: Cash & cash equivalent | E88: 3804 | F88: 8669 | G88: 5595
B89: Short term investments | E89: 73218 | F89: 77040 | G89: 90931
B90: Accounts recievable | E90: 17486 | F90: 19544 | G90: 17908
B91: Invnetories | E91: 1938 | F91: 2660 | G91: 2902
B92: Deferred income tax | E92: 1632 | F92: 1941 | G92: 1915
B93: Other | E93: 3388 | F93: 4392 | G93: 5461
B94: Total current assets | E94: =SUM(E88:E93) -> 101466 | F94: =SUM(F88:F93) -> 114246 | G94: =SUM(G88:G93) -> 124712
B96: Property & equipment | E96: 9991 | F96: 13011 | G96: 14731
B97: Equity and other investments | E97: 10844 | F97: 14597 | G97: 12053
B98: Goodwill | E98: 14655 | F98: 20127 | G98: 16939
B99: Intangible assets,net | E99: 3083 | F99: 6981 | G99: 4835
B100: Other long term assets | E100: 2392 | F100: 3422 | G100: 2953
B101: Total assets | E101: =E94+SUM(E96:E100) -> 142431 | F101: =F94+SUM(F96:F100) -> 172384 | G101: =G94+SUM(G96:G100) -> 176223
B103: Liabilities & stockholders equity
B104: Current liabilities
B105: Accouunts payables | E105: 4828 | F105: 7432 | G105: 6591
B106: Short term debt | E106: - | F106: 2000 | G106: 4985
B107: Current portion of long term debt | E107: 2999 | F107: - | G107: 2499
B108: Accrued compensation | E108: 4117 | F108: 4797 | G108: 5096
B109: Income taxes | E109: 592 | F109: 782 | G109: 606
B110: Short term unearned revenue | E110: 20639 | F110: 23150 | G110: 23223
B111: Securities lending payable | E111: 645 | F111: 558 | G111: 92
B112: Others | E112: 3597 | F112: 6906 | G112: 6766
B113: Total current liabilities | E113: =SUM(E105:E112) -> 37417 | F113: =SUM(F105:F112) -> 45625 | G113: =SUM(G105:G112) -> 49858
B115: Long term debt | E115: 12601 | F115: 20645 | G115: 27808
B116: Long term unearned revenue | E116: 1760 | F116: 2008 | G116: 2095
B117: Deferred income taxes | E117: 1709 | F117: 2728 | G117: 2835
B118: Other long term liabilities | E118: 10000 | F118: 11594 | G118: 13544
B119: Total liabilities | E119: =E113+SUM(E115:E118) -> 63487 | F119: =F113+SUM(F115:F118) -> 82600 | G119: =G113+SUM(G115:G118) -> 96140
B121: Commitment and contingencies
B122: Stockholders equity
...

Sheet Linked in Target
A2: Merger model of Microsoft & Linked In
A3: Acquirer Company : Microsoft (MSFT)
A4: Tartget Company : LinkedIn (LNKD)
A5: Date of Acquisition : 13/06/2016
A6: Price of acquisition : $26.2 Billion
A7: ($ in million except per share data)
A9: Targets Details
B11: Latest Financials available | F11: 42369 | J11: Capitalisation of leases
B12: Unaffected share price | F12: 131.08 | J12: Year | L12: amount | M12: Lease committed
B13: Transaction date share price | F13: 196 | J13: 2016 | L13: =141471/10^3 -> 141.471
B14: Tax rate | F14: 0.23 | J14: =J13+1 -> 2017 | L14: =150087/10^3 -> 150.087
J15: =J14+1 -> 2018 | L15: 177
B16: Basic shares outstaning | F16: =129024/10^3 -> 129.024 | J16: =J15+1 -> 2019 | L16: 181
B17: Dilutive shares outstanding | F17: =129024/10^3 -> 129.024 | J17: =J16+1 -> 2020 | L17: 175 | M17: =993730/10^3 -> 993.73
J18: =J17+1 -> 2021 | L18: 175 | M18: =M17-L18 -> 818.73
J19: =J18+1 -> 2022 | L19: 175 | M19: =M18-L19 -> 643.73
B20: Equity value on date on transaction | F20: =F17*F13 -> 25288.704 | J20: =J19+1 -> 2023 | L20: 175 | M20: =M19-L20 -> 468.73
B21: Less: Cash | F21: =546237/10^3 -> 546.237 | J21: =J20+1 -> 2024 | L21: 175 | M21: =M20-L21 -> 293.73
B22: Less: Investments | F22: =2573145/10^3 -> 2573.145 | J22: =J21+1 -> 2025 | L22: 175 | M22: =M21-L22 -> 118.73
B23: Add: Debt | F23: =1126534/10^3 -> 1126.534 | J23: =J22+1 -> 2026 | L23: 119 | M23: =M22-L23 -> -0.27
B24: Add: Capitalisation of lease | F24: =L27 -> 1408.6829
B25: Add: Preference shares | F25: 0
B26: Add: NCI | F26: =26810/10^3 -> 26.81 | J26: Cost of debt | L26: =L31 -> 0.045166857
B27: Add: Unfunded pension obligation | F27: 0 | J27: PV of lease obligation | L27: =NPV(L26,L13:L23) -> 1408.6829
B28: Enterprise value | F28: =SUM(F20:F27) -> 30970.113
J29: total debt | L29: =F23 -> 1126.534
J30: interest expense | L30: =50882/10^3 -> 50.882
J31: Cost of debt | L31: =L30/L29 -> 0.045166857
A33: Targets Income Statement | H33: Historical | L33: Projection
A34: (In millions) | G34: 2013 | H34: =G34+1 -> 2014 | I34: =H34+1 -> 2015 | J34: =I34+1 -> 2016 | K34: =J34+1 -> 2017 | L34: =K34+1 -> 2018 | M34: =L34+1 -> 2019 | N34: =M34+1 -> 2020
B36: Net revenue | F36: 972309 | G36: 1528545 | H36: 2218767 | I36: 2990911 | J36: =I36*(1+J69) -> 4358393.6 | K36: =J36*(1+K69) -> 6184231.5 | L36: =K36*(1+L69) -> 8707693.1 | M36: =L36*(1+M69) -> 12435123 | N36: =M36*(1+N69) -> 17637289
B37: Cost of revenue | F37: 125521 | G37: 202908 | H37: 293797 | I37: 418858 | J37: =J36*J70 -> 588679.51 | K37: =K36*K70 -> 840078.69 | L37: =L36*L70 -> 1192819.5 | M37: =M36*M70 -> 1690739.8 | N37: =N36*N70 -> 2403324.5
B38: Gross Profit | F38: =F36-F37 -> 846788 | G38: =G36-G37 -> 1325637 | H38: =H36-H37 -> 1924970 | I38: =I36-I37 -> 2572053 | J38: =J36-J37 -> 3769714.1 | K38: =K36-K37 -> 5344152.8 | L38: =L36-L37 -> 7514873.6 | M38: =M36-M37 -> 10744383 | N38: =N36-N37 -> 15233965
B40: Sales and marketing | G40: 522100 | H40: 774411 | I40: 1048129 | J40: =J36*J71 -> 1512409.6 | K40: =K36*K71 -> 2157217.6 | L40: =L36*L71 -> 3036878.5 | M40: =M36*M71 -> 4329886.3 | N40: =N36*N71 -> 6148251.5
B41: Product development | G41: 395643 | H41: 536184 | I41: 775660 | J41: =J36*J72 -> 1103885.1 | K41: =K36*K72 -> 1554871.6 | L41: =L36*L72 -> 2217681.7 | M41: =M36*M72 -> 3147677.3 | N41: =N36*N72 -> 4463609.3
B42: General and administrative | G42: 225566 | H42: 341294 | I42: 478734 | J42: =J36*J73 -> 670398.66 | K42: =K36*K73 -> 964126.31 | L42: =L36*L73 -> 1363571.1 | M42: =M36*M73 -> 1932884 | N42: =N36*N73 -> 2751017.7
B43: Depreciation and amortization | G43: 134516 | H43: 236946 | I43: 420472 | J43: =J36*J74 -> 487235.92 | K43: =K36*K74 -> 740391.75 | L43: =L36*L74 -> 1080039.3 | M43: =M36*M74 -> 1473760.3 | N43: =N36*N74 -> 2129827.5
B44: Total costs and expenses | G44: =SUM(G40:G43) -> 1277825 | H44: =SUM(H40:H43) -> 1888835 | I44: =SUM(I40:I43) -> 2722995 | J44: =SUM(J40:J43) -> 3773929.2 | K44: =SUM(K40:K43) -> 5416607.2 | L44: =SUM(L40:L43) -> 7698170.6 | M44: =SUM(M40:M43) -> 10884208 | N44: =SUM(N40:N43) -> 15492706
B45: Income (loss) from operations (EBIT) | G45: =G38-G44 -> 47812 | H45: =H38-H44 -> 36135 | I45: =I38-I44 -> -150942 | J45: =J38-J44 -> -4215.1567 | K45: =K38-K44 -> -72454.376 | L45: =L38-L44 -> -183297 | M45: =M38-M44 -> -139825.2 | N45: =N38-N44 -> -258741.21
B46: Other income (expense), net:
B47: Interest income | G47: 2895 | H47: 4971 | I47: 10571
B48: Interest expense | G48: 0 | H48: -6797 | I48: -50882
B49: Other, net | G49: -1479 | H49: -3104 | I49: -23477
B50: Total other income (expense), net | G50: =SUM(G47:G49) -> 1416 | H50: =SUM(H47:H49) -> -4930 | I50: =SUM(I47:I49) -> -63788 | J50: =J36*J76 -> 4037.4901 | K50: =K36*K76 -> 5728.8937 | L50: =L36*L76 -> 8066.5557 | M50: =M36*M76 -> 11519.539 | N50: =N36*N76 -> 16338.676
B52: Income (loss) before income taxes | G52: =G45+G50 -> 49228 | H52: =H45+H50 -> 31205 | I52: =I45+I50 -> -214730 | J52: =J45+J50 -> -177.66656 | K52: =K45+K50 -> -66725.482 | L52: =L45+L50 -> -175230.44 | M52: =M45+M50 -> -128305.66 | N52: =N45+N50 -> -242402.53
B53: Provision (benefit) for income taxes | G53: 22459 | H53: 46525 | I53: -49969 | J53: =J52*J75 -> -41.344108 | K53: =K52*K75 -> -15527.433 | L53: =L52*L75 -> -40777.208 | M53: =M52*M75 -> -29857.521 | N53: =N52*N75 -> -56408.57
B54: Net income (loss) PAT | G54: =G52-G53 -> 26769 | H54: =H52-H53 -> -15320 | I54: =I52-I53 -> -164761 | J54: =J52-J53 -> -136.32245 | K54: =K52-K53 -> -51198.049 | L54: =L52-L53 -> -134453.23 | M54: =M52-M53 -> -98448.138 | N54: =N52-N53 -> -185993.96
B56: Accretion of redeemable noncontrolling interest | G56: 0 | H56: -427 | I56: -1383 | J56: 0 | K56: 0 | L56: 0 | M56: 0 | N56: 0
B57: Net income (loss) attributable to common stockholders | G57: =G54+G56 -> 26769 | H57: =H54+H56 -> -15747 | I57: =I54+I56 -> -166144 | J57: =J54+J56 -> -136.32245 | K57: =K54+K56 -> -51198.049 | L57: =L54+L56 -> -134453.23 | M57: =M54+M56 -> -98448.138 | N57: =N54+N56 -> -185993.96
B59: Basic Share Outstanding | G59: 113643 | H59: 122800 | I59: 129024 | J59: 129024 | K59: 129024 | L59: 129024 | M59: 129024 | N59: 129024
B60: Diluted Share Outstanding | G60: 118944 | H60: 122800 | I60: 129024 | J60: 129024 | K60: 129024 | L60: 129024 | M60: 129024 | N60: 129024
B62: Basic EPS | G62: =G54/G59 -> 0.23555344 | H62: =H54/H59 -> -0.1247557 | I62: =I54/I59 -> -1.2769795 | J62: =J54/J59 -> -0.0010565666 | K62: =K54/K59 -> -0.39681028 | L62: =L54/L59 -> -1.0420793 | M62: =M54/M59 -> -0.7630219 | N62: =N54/N59 -> -1.4415455
B63: Diluted EPS | G63: =G54/G60 -> 0.22505549 | H63: =H54/H60 -> -0.1247557 | I63: =I54/I60 -> -1.2769795 | J63: =J54/J60 -> -0.0010565666 | K63: =K54/K60 -> -0.39681028 | L63: =L54/L60 -> -1.0420793 | M63: =M54/M60 -> -0.7630219 | N63: =N54/N60 -> -1.4415455
H66: Historical | L66: Projection
A67: Income Statement Driver | G67: 2013 | H67: =G67+1 -> 2014 | I67: =H67+1 -> 2015 | J67: =I67+1 -> 2016 | K67: =J67+1 -> 2017 | L67: =K67+1 -> 2018 | M67: =L67+1 -> 2019 | N67: =M67+1 -> 2020
B69: Sales growth rate | G69: =G36/F36-1 -> 0.5720774 | H69: =H36/G36-1 -> 0.45155491 | I69: =I36/H36-1 -> 0.3480059 | J69: =AVERAGE(G69:I69) -> 0.45721273 | K69: =AVERAGE(H69:J69) -> 0.41892451 | L69: =AVERAGE(I69:K69) -> 0.40804771 | M69: =AVERAGE(J69:L69) -> 0.42806165 | N69: =AVERAGE(K69:M69) -> 0.41834463
B70: Cost of revenue as % of sales | G70: =G37/G36 -> 0.13274585 | H70: =H37/H36 -> 0.13241453 | I70: =I37/I36 -> 0.14004362 | J70: =AVERAGE(G70:I70) -> 0.135068 | K70: =AVERAGE(H70:J70) -> 0.13584205 | L70: =AVERAGE(I70:K70) -> 0.13698456 | M70: =AVERAGE(J70:L70) -> 0.13596487 | N70: =AVERAGE(K70:M70) -> 0.13626383
B71: Sales and marketing as % of sales | G71: =G40/G36 -> 0.34156665 | H71: =H40/H36 -> 0.34902764 | I71: =I40/I36 -> 0.35043804 | J71: =AVERAGE(G71:I71) -> 0.34701078 | K71: =AVERAGE(H71:J71) -> 0.34882549 | L71: =AVERAGE(I71:K71) -> 0.3487581 | M71: =AVERAGE(J71:L71) -> 0.34819812 | N71: =AVERAGE(K71:M71) -> 0.3485939
B72: Product development as % of sales | G72: =G41/G36 -> 0.25883634 | H72: =H41/H36 -> 0.24165854 | I72: =I41/I36 -> 0.25933904 | J72: =AVERAGE(G72:I72) -> 0.25327798 | K72: =AVERAGE(H72:J72) -> 0.25142519 | L72: =AVERAGE(I72:K72) -> 0.25468074 | M72: =AVERAGE(J72:L72) -> 0.25312797 | N72: =AVERAGE(K72:M72) -> 0.25307796
B73: General and administrative as % of sales | G73: =G42/G36 -> 0.14756909 | H73: =H42/H36 -> 0.15382147 | I73: =I42/I36 -> 0.16006294 | J73: =AVERAGE(G73:I73) -> 0.15381783 | K73: =AVERAGE(H73:J73) -> 0.15590075 | L73: =AVERAGE(I73:K73) -> 0.15659384 | M73: =AVERAGE(J73:L73) -> 0.15543747 | N73: =AVERAGE(K73:M73) -> 0.15597735
B74: Dep and Amortization as %age of sales | G74: =G84/G36 -> 0.088002643 | H74: =H84/H36 -> 0.10679175 | I74: =I84/I36 -> 0.14058325 | J74: =AVERAGE(G74:I74) -> 0.11179255 | K74: =AVERAGE(H74:J74) -> 0.11972252 | L74: =AVERAGE(I74:K74) -> 0.12403277 | M74: =AVERAGE(J74:L74) -> 0.11851594 | N74: =AVERAGE(K74:M74) -> 0.12075708
B75: Provision for income taxes as % of PBT | G75: =G53/G52 -> 0.4562241 | H75: =H53/H52 -> 1.490947 | I75: =I53/I52 -> 0.23270619 | J75: 0.23270619 | K75: 0.23270619 | L75: 0.23270619 | M75: 0.23270619 | N75: 0.23270619
B76: Other income(expense) as a % of operating income | G76: =G50/G36 -> 0.00092637116 | H76: =H50/H36 -> -0.0022219548 | I76: =I50/I36 -> -0.021327281 | J76: 0.00092637116 | K76: 0.00092637116 | L76: 0.00092637116 | M76: 0.00092637116 | N76: 0.00092637116
H80: Historical | L80: Projection
A81: Key metrixs | G81: 2013 | H81: =G81+1 -> 2014 | I81: =H81+1 -> 2015 | J81: =I81+1 -> 2016 | K81: =J81+1 -> 2017 | L81: =K81+1 -> 2018 | M81: =L81+1 -> 2019 | N81: =M81+1 -> 2020
B83: EBIT | G83: =G45 -> 47812 | H83: =H45 -> 36135 | I83: =I45 -> -150942 | J83: =J45 -> -4215.1567 | K83: =K45 -> -72454.376 | L83: =L45 -> -183297 | M83: =M45 -> -139825.2 | N83: =N45 -> -258741.21
B84: add: Depriciation and amortisation | G84: 134516 | H84: 236946 | I84: 420472 | J84: =J74*J36 -> 487235.92 | K84: =K74*K36 -> 740391.75 | L84: =L74*L36 -> 1080039.3 | M84: =M74*M36 -> 1473760.3 | N84: =N74*N36 -> 2129827.5
B85: EBITDA | G85: =G83+G84 -> 182328 | H85: =H83+H84 -> 273081 | I85: =I83+I84 -> 269530 | J85: =J83+J84 -> 483020.77 | K85: =K83+K84 -> 667937.38 | L85: =L83+L84 -> 896742.31 | M85: =M83+M84 -> 1333935.1 | N85: =N83+N84 -> 1871086.3
B87: Gross margin | G87: =G38/G36 -> 0.86725415 | H87: =H38/H36 -> 0.86758547 | I87: =I38/I36 -> 0.85995638 | J87: =J38/J36 -> 0.864932 | K87: =K38/K36 -> 0.86415795 | L87: =L38/L36 -> 0.86301544 | M87: =M38/M36 -> 0.86403513 | N87: =N38/N36 -> 0.86373617
B88: EBIT Margin | G88: =G83/G36 -> 0.031279419 | H88: =H83/H36 -> 0.016286072 | I88: =I83/I36 -> -0.050466898 | J88: =J83/J36 -> -0.00096713539 | K88: =K83/K36 -> -0.011715987 | L88: =L83/L36 -> -0.021050007 | M88: =M83/M36 -> -0.011244376 | N88: =N83/N36 -> -0.014670123
B89: EBITDA margin | G89: =G85/G36 -> 0.11928206 | H89: =H85/H36 -> 0.12307782 | I89: =I85/I36 -> 0.090116356 | J89: =J85/J36 -> 0.11082541 | K89: =K85/K36 -> 0.10800653 | L89: =L85/L36 -> 0.10298277 | M89: =M85/M36 -> 0.10727157 | N89: =N85/N36 -> 0.10608695
B90: Net margin | G90: =G54/G36 -> 0.017512733 | H90: =H54/H36 -> -0.0069047358 | I90: =I54/I36 -> -0.055087229 | J90: =J54/J36 -> -3.1278142e-05 | K90: =K54/K36 -> -0.0082788054 | L90: =L54/L36 -> -0.015440741 | M90: =M54/M36 -> -0.0079169415 | N90: =N54/N36 -> -0.010545496
B92: Effective tax rate | G92: 0.23 | H92: 1.49 | I92: 0.46 | J92: 0.46 | K92: 0.46 | L92: 0.46 | M92: 0.46 | N92: 0.46
A96: Targets balance sheet | H96: Historical | L96: Projection
A97: (In millions) | G97: 2013 | H97: =G97+1 -> 2014 | I97: =H97+1 -> 2015 | J97: =I97+1 -> 2016 | K97: =J97+1 -> 2017 | L97: =K97+1 -> 2018 | M97: =L97+1 -> 2019 | N97: =M97+1 -> 2020
B99: Assets
B100: Current Assets:
B101: Cash and cash equivalents | G101: 803089 | H101: 460887 | I101: 546237
B102: Marketable securities | G102: 1526212 | H102: 2982422 | I102: 2573145
B103: Accounts receivable | G103: 302168 | H103: 449048 | I103: 603060
B104: Deferred commissions | G104: 47496 | H104: 66561 | I104: 87706
B105: Prepaid expenses | G105: 32114 | H105: 52978 | I105: 62992
B106: Other current assets | G106: 44391 | H106: 110204 | I106: 61949
B107: Total current assets | G107: =SUM(G101:G106) -> 2755470 | H107: =SUM(H101:H106) -> 4122100 | I107: =SUM(I101:I106) -> 3935089
B109: Property and equipment, net | G109: 361741 | H109: 740909 | I109: 1047005
B110: Goodwill | G110: 150871 | H110: 356718 | I110: 1507093
B111: Intangible assets, net | G111: 43046 | H111: 131275 | I111: 373087
B112: Other assets | G112: 41665 | H112: 76255 | I112: 148925
B113: Total Assets | G113: =SUM(G107:G112) -> 3352793 | H113: =SUM(H107:H112) -> 5427257 | I113: =SUM(I107:I112) -> 7011199
B115: Liabilities & Stockholders' Equity
B116: Current liabilities:
B117: Accounts payable | G117: 66744 | H117: 100297 | I117: 162176
B118: Accrued liabilities | G118: 183004 | H118: 260189 | I118: 316792
B119: Deferred revenue | G119: 392243 | H119: 522299 | I119: 709116
B120: Total current liabilities | G120: =SUM(G117:G119) -> 641991 | H120: =SUM(H117:H119) -> 882785 | I120: =SUM(I117:I119) -> 1188084
B122: Convertible senior notes, net | G122: - | H122: 1081553 | I122: 1126534
B123: Deferred tax liabilities | G123: 14879 | H123: - | I123: -
B124: Other long term liabilities | G124: 61529 | H124: 132100 | I124: 201128
B125: Total liabilities | G125: =SUM(G120:G124) -> 718399 | H125: =SUM(H120:H124) -> 2096438 | I125: =SUM(I120:I124) -> 2515746
B127: Redeemable non-controlling interest | G127: 5000 | H127: 5427 | I127: 26810
...

Sheet Merger Model
A3: Merger model of Microsoft & Linked In
A4: Acquirer Company : Microsoft (MSFT)
A5: Tartget Company : LinkedIn (LNKD)
A6: ($ in million except per share data)
A8: Transacation assumptions
B10: Date of announcement of merger | G10: June 13, 2016
B11: Date of complition of merger | G11: Dec 08, 2016
I12: %Cash | J12: 0 | L12: Particular | N12: Amount | O12: Pre-tax cost | P12: Tax rate of acquirer | Q12: Post tax cost
B13: Acquirer Company | G13: Microsoft Corp. | I13: %Debt | J13: 1 | L13: Cash used | N13: =J12*G27 -> 0 | O13: =766/AVERAGE('Microsoft acquirer'!F88:G88) -> 0.10740325 | P13: ='Microsoft acquirer'!$D$14 -> 0.34 | Q13: =O13*(1-P13) -> 0.070886147
B14: Acquirer's Ticker | G14: (Nasdaq: MSFT) | I14: %Stock | J14: 0 | L14: Debt used | N14: =J13*G27 -> 25288.704 | O14: 0.027 | P14: ='Microsoft acquirer'!$D$14 -> 0.34 | Q14: =O14*(1-P14) -> 0.01782
L15: Stock used | N15: 0 | P15: ='Microsoft acquirer'!$D$14 -> 0.34 | Q15: ='Microsoft acquirer'!G50/'Microsoft acquirer'!D13 -> 0.02946197
B16: Tartget Company | G16: LinkedIn Corporation | L16: No. of share issued
B17: Target's Ticker | G17: (NYSE: LNKD) | L17: Weighted average cost of fund | Q17: =SUMPRODUCT(N13:N15,Q13:Q15)/SUM(N13:N15) -> 0.01782
B19: Unaffected share price | G19: 131 | L19: Year | M19: 2017 | N19: 2018 | O19: 2019 | P19: 2020
B20: Offer Price | G20: 196 | L20: COGS Synergies | M20: 30 | N20: 30 | O20: 30 | P20: 30
B21: Premium | G21: =G20-G19 -> 65
B22: Premium % | G22: =G21/G19 -> 0.49618321
I23: EMI | J23: =PMT(O14,G32,-N14,0,0) -> 5474.692 | L23: Year | M23: EMI | N23: Interest | O23: Principal | P23: closing balance
B24: Equity Value | L24: 2017 | M24: =$J$23 -> 5474.692 | N24: =O14*N14 -> 682.79501 | O24: =M24-N24 -> 4791.897 | P24: =N14-O24 -> 20496.807
B25: No.of Diluted shares outstanding | G25: ='Linked in Target'!F17 -> 129.024 | L25: =L24+1 -> 2018 | M25: =$J$23 -> 5474.692 | N25: =P24*$O$14 -> 553.41379 | O25: =M25-N25 -> 4921.2782 | P25: =P24-O25 -> 15575.529
L26: =L25+1 -> 2019 | M26: =$J$23 -> 5474.692 | N26: =P25*$O$14 -> 420.53928 | O26: =M26-N26 -> 5054.1527 | P26: =P25-O26 -> 10521.376
B27: purchase equity value | G27: ='Linked in Target'!F20 -> 25288.704 | L27: =L26+1 -> 2020 | M27: =$J$23 -> 5474.692 | N27: =P26*$O$14 -> 284.07716 | O27: =M27-N27 -> 5190.6148 | P27: =P26-O27 -> 5330.7614
B28: purchase enterprice value | G28: ='Linked in Target'!$F$28 -> 30970.113 | L28: =L27+1 -> 2021 | M28: =$J$23 -> 5474.692 | N28: =P27*$O$14 -> 143.93056 | O28: =M28-N28 -> 5330.7614 | P28: =P27-O28 -> 0
B30: Advisory fees | G30: 0.01
B31: Debt Issuance fees | G31: 0.03
B32: Amortization period (year) | G32: 5
B34: Minimum cash balance of combined company | G34: 1000
B35: Pre-deal cash balance of combined company | G35: 97072
A37: Sources and uses of fund
C39: Sources of Funds | J39: Uses of Funds
B40: Cash | E40: =N13 -> 0 | I40: Equity purchase price | K40: ` | L40: =G27 -> 25288.704
B41: Debt | E41: =N14 -> 25288.704 | I41: Advisory fees | L41: =G30*L40 -> 252.88704
B42: Equity | E42: =N15 -> 0 | I42: Debt issuance fees | L42: =G31*N14 -> 758.66112
B43: Excess Cash | E43: =E44-SUM(E40:E42) -> 859.81594 | I43: Refinancing of acquirer's debt
B44: Total | E44: =L44 -> 26148.52 | I44: Total | L44: 26148.52
A46: Purchase Price Allocation
I47: `
B48: Calculation of goodwill: | I48: Fixed Asset writeup
B49: Equity Purchase price | F49: =G27 -> 25288.704 | I49: PPE writeup in % | K49: 0.1
B50: Less: Book value of target's equity | F50: ='Linked in Target'!I128/10^3 -> 4468.643 | I50: PPE writeup in amount | K50: =K49*'Linked in Target'!I109/10^3 -> 104.7005
B51: Add: Existing goodwill of target | F51: ='Linked in Target'!I110/10^3 -> 1507.093 | I51: Life of a fixed asset (year) | K51: 10
B52: Allocated Purchase Price | F52: =F49+F51-F50 -> 22327.154
B54: Less: Fixed asset writeup | F54: =-K50 -> -104.7005 | I54: Intangible assets identified
B55: Less: Intangible asset (Finite life) | F55: =-K56 -> -7887 | I55: Other intangible asset % | K55: =K56/F52 -> 0.35324699
B56: Less DTL Written off | F56: -1327 | I56: Other intangible asset amount | K56: 7887
B57: Add: New DTL created | F57: =K59 -> 2717.1782 | I57: Life of intangible assets (years) | K57: 10
B58: Goodwill | F58: =SUM(F52:F57) -> 15725.632
I59: New DTL created | K59: =(K56+K50)*'Microsoft acquirer'!$D$14 -> 2717.1782
J61: Forecast
A62: Combined Company's Income Statement | J62: =K62-1 -> 2016 | K62: 2017 | L62: =K62+1 -> 2018 | M62: =L62+1 -> 2019 | N62: =M62+1 -> 2020
B64: Revenue - Acquirer | J64: ='Microsoft acquirer'!H33 -> 100851.25 | K64: ='Microsoft acquirer'!I33 -> 108687.48 | L64: ='Microsoft acquirer'!J33 -> 117132.59 | M64: ='Microsoft acquirer'!K33 -> 126233.89 | N64: ='Microsoft acquirer'!L33 -> 136042.38
B65: Revenue - Target | J65: ='Linked in Target'!J36 -> 4358393.6 | K65: ='Linked in Target'!K36 -> 6184231.5 | L65: ='Linked in Target'!L36 -> 8707693.1 | M65: ='Linked in Target'!M36 -> 12435123 | N65: ='Linked in Target'!N36 -> 17637289
B66: Revenue - Synergies | J66: 0 | K66: 0 | L66: 0 | M66: 0 | N66: 0
B67: Revenue of combined companies | J67: =100851.2+4358.4 -> 105209.6 | K67: =108687+6184 -> 114871 | L67: =117133+8708 -> 125841 | M67: =126234+12435 -> 138669 | N67: =136042+17637 -> 153679
B69: Cost of sales - Acquirer | J69: ='Microsoft acquirer'!H34 -> 31154.247 | K69: ='Microsoft acquirer'!I34 -> 35279.895 | L69: ='Microsoft acquirer'!J34 -> 38519.358 | M69: ='Microsoft acquirer'!K34 -> 40494.357 | N69: ='Microsoft acquirer'!L34 -> 44179.325
B70: Cost of sales - Target | J70: ='Linked in Target'!J37/10^3 -> 588.67951 | K70: ='Linked in Target'!K37/10^3 -> 840.07869 | L70: ='Linked in Target'!L37/10^3 -> 1192.8195 | M70: ='Linked in Target'!M37/10^3 -> 1690.7398 | N70: ='Linked in Target'!N37/10^3 -> 2403.3245
B71: Cost of sales - Synergies | J71: -30 | K71: -30 | L71: -30 | M71: -30 | N71: -30
B72: Cost of sales of combined compines | J72: =SUM(J69:J71) -> 31712.926 | K72: =SUM(K69:K71) -> 36089.974 | L72: =SUM(L69:L71) -> 39682.177 | M72: =SUM(M69:M71) -> 42155.097 | N72: =SUM(N69:N71) -> 46552.65
B74: Gross Profit | J74: =J67-J72 -> 73496.674 | K74: =K67-K72 -> 78781.026 | L74: =L67-L72 -> 86158.823 | M74: =M67-M72 -> 96513.903 | N74: =N67-N72 -> 107126.35
B76: Selling and General expenses - Acquirer | J76: =SUM('Microsoft acquirer'!H37:H40) -> 37223.364 | K76: =SUM('Microsoft acquirer'!I37:I40) -> 39293.135 | L76: =SUM('Microsoft acquirer'!J37:J40) -> 42127.671 | M76: =SUM('Microsoft acquirer'!K37:K40) -> 45876.501 | N76: =SUM('Microsoft acquirer'!L37:L40) -> 49184.154
B77: Selling and General expenses - Target | J77: =SUM('Linked in Target'!J40:J43)/10^3 -> 3773.9292 | K77: =SUM('Linked in Target'!K40:K43)/10^3 -> 5416.6072 | L77: =SUM('Linked in Target'!L40:L43)/10^3 -> 7698.1706 | M77: =SUM('Linked in Target'!M40:M43)/10^3 -> 10884.208 | N77: =SUM('Linked in Target'!N40:N43)/10^3 -> 15492.706
B78: Selling and General expenses - Synergies | J78: 0 | K78: 0 | L78: 0 | M78: 0 | N78: 0
B79: Selling and General expenses of combined companied (Including D&A) | J79: =J76+J77 -> 40997.293 | K79: =K76+K77 -> 44709.742 | L79: =L76+L77 -> 49825.842 | M79: =M76+M77 -> 56760.709 | N79: =N76+N77 -> 64676.86
B80: Depreciation and Amortization - Acquirer | J80: ='Microsoft acquirer'!H74 -> 5779.2616 | K80: ='Microsoft acquirer'!I74 -> 6556.9285 | L80: ='Microsoft acquirer'!J74 -> 7078.3167 | M80: ='Microsoft acquirer'!K74 -> 7492.5303 | N80: ='Microsoft acquirer'!L74 -> 8167.6478
B81: Depreciation and Amortization - Target | J81: ='Linked in Target'!J84/10^3 -> 487.23592 | K81: ='Linked in Target'!K84/10^3 -> 740.39175 | L81: ='Linked in Target'!L84/10^3 -> 1080.0393 | M81: ='Linked in Target'!M84/10^3 -> 1473.7603 | N81: ='Linked in Target'!N84/10^3 -> 2129.8275
B82: Selling and General expenses of combined companied (Excluding D&A) | J82: =J79-SUM(J80:J81) -> 34730.796 | K82: =K79-SUM(K80:K81) -> 37412.422 | L82: =L79-SUM(L80:L81) -> 41667.486 | M82: =M79-SUM(M80:M81) -> 47794.419 | N82: =N79-SUM(N80:N81) -> 54379.385
B84: EBITDA of combined companies | J84: =J74-J82 -> 38765.878 | K84: =K74-K82 -> 41368.604 | L84: =L74-L82 -> 44491.337 | M84: =M74-M82 -> 48719.485 | N84: =N74-N82 -> 52746.966
B86: Depreciation and Amortization - Acquirer | J86: 5779.2616 | K86: 6556.9285 | L86: 7078.3167 | M86: 7492.5303 | N86: 8167.6478
B87: Depreciation and Amortization - Target | J87: 487.23592 | K87: 740.39175 | L87: 1080.0393 | M87: 1473.7603 | N87: 2129.8275
B88: Amortization of intangible asset identified in merger | J88: =$K$56/$K$57 -> 788.7 | K88: =$K$56/$K$57 -> 788.7 | L88: =$K$56/$K$57 -> 788.7 | M88: =$K$56/$K$57 -> 788.7 | N88: =$K$56/$K$57 -> 788.7
B89: Dep on fixed asset write up | J89: =$K$50/$K$51 -> 10.47005 | K89: =$K$50/$K$51 -> 10.47005 | L89: =$K$50/$K$51 -> 10.47005 | M89: =$K$50/$K$51 -> 10.47005 | N89: =$K$50/$K$51 -> 10.47005
B91: EBIT of comnbined companies | J91: =J84-SUM(J86:J90) -> 31700.21 | K91: =K84-SUM(K86:K90) -> 33272.114 | L91: =L84-SUM(L86:L90) -> 35533.811 | M91: =M84-SUM(M86:M90) -> 38954.024 | N91: =N84-SUM(N86:N90) -> 41650.32
B93: Interest expense - combined companies | J93: {=TRANSPOSE(N24:N28)} -> 682.79501 | K93: {=TRANSPOSE(N25:N28)} -> 553.41379 | L93: {=TRANSPOSE(N26:N28)} -> 420.53928 | M93: {=TRANSPOSE(N27:N28)} -> 284.07716 | N93: {=TRANSPOSE(N28)} -> 143.93056
B94: Amortization of Debt | J94: =-$N$14/$G$32 -> -5057.7408 | K94: =-$N$14/$G$32 -> -5057.7408 | L94: =-$N$14/$G$32 -> -5057.7408 | M94: =-$N$14/$G$32 -> -5057.7408 | N94: =-$N$14/$G$32 -> -5057.7408
B95: Foregone interest on cash | J95: =-$E$43*$O$13 -> -92.347028 | K95: =-$E$43*$O$13 -> -92.347028 | L95: =-$E$43*$O$13 -> -92.347028 | M95: =-$E$43*$O$13 -> -92.347028 | N95: =-$E$43*$O$13 -> -92.347028
B96: Profit before tax (PBT) | J96: =J91+J93+J94+J95 -> 27232.918 | K96: =K91+K93+K94+K95 -> 28675.44 | L96: =L91+L93+L94+L95 -> 30804.263 | M96: =M91+M93+M94+M95 -> 34088.013 | N96: =N91+N93+N94+N95 -> 36644.163
B97: Provision for tax | J97: =J96*'Microsoft acquirer'!$D$14 -> 9259.192 | K97: =K96*'Microsoft acquirer'!$D$14 -> 9749.6495 | L97: =L96*'Microsoft acquirer'!$D$14 -> 10473.449 | M97: =M96*'Microsoft acquirer'!$D$14 -> 11589.925 | N97: =N96*'Microsoft acquirer'!$D$14 -> 12459.015
B98: Profit after tax (PAT) | J98: =J96-J97 -> 17973.726 | K98: =K96-K97 -> 18925.79 | L98: =L96-L97 -> 20330.813 | M98: =M96-M97 -> 22498.089 | N98: =N96-N97 -> 24185.148
B99: Non-controlling interest | J99: 0 | K99: 0 | L99: 0 | M99: 0 | N99: 0
B100: Net earnings per common share attributable to common shareholders: | J100: =SUM(J98:J99) -> 17973.726 | K100: =SUM(K98:K99) -> 18925.79 | L100: =SUM(L98:L99) -> 20330.813 | M100: =SUM(M98:M99) -> 22498.089 | N100: =SUM(N98:N99) -> 24185.148
B102: Diluted share outstanding | J102: ='Microsoft acquirer'!H54:L54 -> 8254 | K102: ='Microsoft acquirer'!I54:M54 -> 8254 | L102: ='Microsoft acquirer'!J54:N54 -> 8254 | M102: =L102 -> 8254 | N102: 8254
B103: EPS-combined company | J103: =J100/J102 -> 2.1775776 | K103: =K100/K102 -> 2.2929234 | L103: =L100/L102 -> 2.4631467 | M103: =M100/M102 -> 2.7257195 | N103: =N100/N102 -> 2.9301124
B104: EPS-Standalone | J104: ='Microsoft acquirer'!H50 -> 2.9960848 | K104: ='Microsoft acquirer'!I50 -> 3.1473752 | L104: ='Microsoft acquirer'!J50 -> 3.3755054 | M104: ='Microsoft acquirer'!K50 -> 3.6811862 | N104: ='Microsoft acquirer'!L50 -> 3.9424115
B105: Accretion/(Dilution) | J105: =J103-J104 -> -0.81850719 | K105: =K103-K104 -> -0.85445175 | L105: =L103-L104 -> -0.91235863 | M105: =M103-M104 -> -0.95546669 | N105: =N103-N104 -> -1.0122991
A107: Combined company's debt schedule | J107: =K107-1 -> 2016 | K107: 2017 | L107: =K107+1 -> 2018 | M107: =L107+1 -> 2019 | N107: =M107+1 -> 2020
B108: Opening Balance | J108: =E41 -> 25288.704 | K108: =J111 -> 20496.807 | L108: =K111 -> 15575.529 | M108: =L111 -> 10521.376 | N108: =M111 -> 5330.7614
B109: Add: Loan Taken
B110: Less: Loan repaid | J110: {=TRANSPOSE(O24:O28)} -> 4791.897 | K110: {=TRANSPOSE(O25:O28)} -> 4921.2782 | L110: {=TRANSPOSE(O26:O28)} -> 5054.1527 | M110: {=TRANSPOSE(O27:O28)} -> 5190.6148 | N110: {=TRANSPOSE(O28)} -> 5330.7614
B111: Closing Balance | J111: =J108-J110 -> 20496.807 | K111: =K108-K110 -> 15575.529 | L111: =L108-L110 -> 10521.376 | M111: =M108-M110 -> 5330.7614 | N111: =N108-N110 -> 0

Sheet Combine balance sheet
A2: Merger model of Microsoft & Linked In
A3: Acquirer Company : Microsoft (MSFT)
A4: Tartget Company : LinkedIn (LNKD)
A5: Date of Acquisition : 13/06/2016
A6: Price of acquisition : $26.2 Billion
A7: (In millions)
A9: Combined balance sheet | E9: 2016 | F9: 2016 | G9: Debit | H9: Credit | J9: 2016
A10: (In millions) | E10: Buyer | F10: Seller | G10: Proforma Adjustments | J10: Combined balance sheet
B12: ASSETS | E12: `
B13: Current Assets
B14: Cash and cash equivalents | E14: 6510 | F14: 546.24 | G14: 0 | H14: ='Merger Model'!E43 -> 859.81594 | J14: =SUM(E14:H14) -> 7916.0559
B15: Short-term investments | E15: 106730 | F15: 2573.15 | G15: 0 | H15: 0 | J15: =SUM(E15:H15) -> 109303.15
B16: Accounts receivable | E16: 18277 | F16: 603.06 | G16: 0 | H16: 0 | J16: =SUM(E16:H16) -> 18880.06
B17: Inventories | E17: 2251 | F17: - | G17: 0 | H17: 0 | J17: =SUM(E17:H17) -> 2251
B18: Deferred commissions | E18: - | F18: 87.71 | G18: 0 | H18: 0 | J18: =SUM(E18:H18) -> 87.71
B19: Other Current Assets and Prepaid Expenses | E19: 5892 | F19: 124.94 | G19: 0 | H19: 0 | J19: =SUM(E19:H19) -> 6016.94
B20: Total current assets | E20: =SUM(E14:E19) -> 139660 | F20: =SUM(F14:F19) -> 3935.1 | J20: =SUM(E20:H20) -> 143595.1
B22: Non-Current Assets
B23: Property and equipment, net | E23: 18356 | F23: 1047.01 | G23: ='Merger Model'!$K$50 -> 104.7005 | H23: 0 | J23: =SUM(E23:H23) -> 19507.71
B24: Goodwill | E24: 17872 | F24: 1507.09 | G24: ='Merger Model'!$F$58 -> 15725.632 | J24: =SUM(E24:H24) -> 35104.722
B25: Intangible assets, net | E25: 3733 | F25: 373.09 | G25: 7887 | H25: 0 | J25: =SUM(E25:H25) -> 11993.09
B26: Equity and other investments | E26: 10431 | F26: - | G26: 0 | H26: 0 | J26: =SUM(E26:H26) -> 10431
B27: Other long-term assets | E27: 3642 | F27: 148.93 | G27: 0 | H27: 0 | J27: =SUM(E27:H27) -> 3790.93
B28: Total assets | E28: =SUM(E20:E27) -> 193694 | F28: =SUM(F20:F27) -> 7011.22 | G28: 0 | H28: 0 | J28: =SUM(E28:H28) -> 200705.22
B30: LIABILITY AND EQUITY
B31: Current Liability
B32: Accounts payables | E32: 6898 | F32: 162.18 | G32: 0 | H32: 0 | J32: =SUM(E32:H32) -> 7060.18
B33: Short-term debt | E33: 12904 | F33: - | G33: 0 | H33: 0 | J33: =SUM(E33:H33) -> 12904
B34: Accrued compensation | E34: 5264 | F34: - | G34: 0 | H34: 0 | J34: =SUM(E34:H34) -> 5264
B35: Accrued liabilities | E35: - | F35: 316.79 | G35: 0 | H35: 0 | J35: =SUM(E35:H35) -> 316.79
B36: Income taxes | E36: 580 | F36: - | G36: 0 | H36: 0 | J36: =SUM(E36:H36) -> 580
B37: Short-term unearned revenue | E37: 27468 | F37: - | G37: 0 | H37: 0 | J37: =SUM(E37:H37) -> 27468
B38: Securities lending payable | E38: 294 | F38: - | G38: 0 | H38: 0 | J38: =SUM(E38:H38) -> 294
B39: Other | E39: 5949 | F39: - | G39: 0 | H39: 0 | J39: =SUM(E39:H39) -> 5949
B40: Deferred revenue | E40: - | F40: 709.12 | G40: 0 | H40: 0 | J40: =SUM(E40:H40) -> 709.12
B41: Total Current Liability | E41: =SUM(E32:E40) -> 59357 | F41: =SUM(F32:F40) -> 1188.09 | G41: 0 | H41: 0 | J41: =SUM(E41:H41) -> 60545.09
B43: Non-Current Liability
B44: New debt taken | E44: 0 | F44: 0 | H44: ='Merger Model'!N14 -> 25288.704 | J44: =SUM(E44:H44) -> 25288.704
B45: Long-term debt | E45: 40783 | F45: 1126.53 | G45: =-F45 -> -1126.53 | H45: ='Merger Model'!F57 -> 2717.1782 | J45: =SUM(E45:H45) -> 43500.178
B46: Long-term unearned revenue | E46: 6441 | F46: - | G46: 0 | H46: 0 | J46: =SUM(E46:H46) -> 6441
B47: Deferred income taxes | E47: 1476 | F47: - | G47: 0 | H47: ='Merger Model'!F57 -> 2717.1782 | J47: =SUM(E47:H47) -> 4193.1782
B48: Other long-term liabilities | E48: 13640 | F48: 201.13 | H48: 0 | J48: =SUM(E48:H48) -> 13841.13
B49: Total Liability | E49: =SUM(E41:E48) -> 121697 | F49: =SUM(F41:F48) -> 2515.75 | J49: =SUM(E49:H49) -> 124212.75
B51: Equity
B52: Total share holder's equity | E52: 71997 | F52: 4495.45 | G52: =F52-'Merger Model'!I46+'[1]Combined Balancesheet'!$G$52 -> -133.2298 | H52: 0 | J52: =SUM(E52:H52) -> 76359.22
G53: 0 | H53: 0
B54: Total Equity and Liability | E54: =E52+E49 -> 193694 | F54: =F52+F49 -> 7011.2 | J54: =SUM(E54:H54) -> 200705.2
B55: Check | E55: =E28-E54 -> 0 | F55: 0 | G55: =G28-G54 -> 0 | H55: =H28-H54 -> 0 | I55: =I28-I54 -> 0 | J55: 0
